AUTHORS
LICENCE
MANIFEST.in
README.rst
RELEASE-NOTES
electrum-chi.desktop
run_electrum_chi
setup.py
Electrum_CHI.egg-info/PKG-INFO
Electrum_CHI.egg-info/SOURCES.txt
Electrum_CHI.egg-info/dependency_links.txt
Electrum_CHI.egg-info/requires.txt
Electrum_CHI.egg-info/top_level.txt
contrib/requirements/requirements-hw.txt
contrib/requirements/requirements.txt
electrum_chi/electrum/__init__.py
electrum_chi/electrum/address_synchronizer.py
electrum_chi/electrum/auxpow.py
electrum_chi/electrum/base_crash_reporter.py
electrum_chi/electrum/base_wizard.py
electrum_chi/electrum/bip32.py
electrum_chi/electrum/bitcoin.py
electrum_chi/electrum/blockchain.py
electrum_chi/electrum/checkpoints.json
electrum_chi/electrum/checkpoints_testnet.json
electrum_chi/electrum/coinchooser.py
electrum_chi/electrum/commands.py
electrum_chi/electrum/compatibility_rpc.py
electrum_chi/electrum/constants.py
electrum_chi/electrum/contacts.py
electrum_chi/electrum/crypto.py
electrum_chi/electrum/currencies.json
electrum_chi/electrum/daemon.py
electrum_chi/electrum/difficulty.py
electrum_chi/electrum/dnssec.py
electrum_chi/electrum/ecc.py
electrum_chi/electrum/ecc_fast.py
electrum_chi/electrum/electrum-chi
electrum_chi/electrum/exchange_rate.py
electrum_chi/electrum/i18n.py
electrum_chi/electrum/interface.py
electrum_chi/electrum/json_db.py
electrum_chi/electrum/jsonrpc.py
electrum_chi/electrum/keystore.py
electrum_chi/electrum/logging.py
electrum_chi/electrum/mnemonic.py
electrum_chi/electrum/msqr.py
electrum_chi/electrum/names.py
electrum_chi/electrum/network.py
electrum_chi/electrum/old_mnemonic.py
electrum_chi/electrum/paymentrequest.proto
electrum_chi/electrum/paymentrequest.py
electrum_chi/electrum/paymentrequest_pb2.py
electrum_chi/electrum/pem.py
electrum_chi/electrum/plot.py
electrum_chi/electrum/plugin.py
electrum_chi/electrum/powdata.py
electrum_chi/electrum/qrscanner.py
electrum_chi/electrum/ripemd.py
electrum_chi/electrum/rsakey.py
electrum_chi/electrum/segwit_addr.py
electrum_chi/electrum/servers.json
electrum_chi/electrum/servers_regtest.json
electrum_chi/electrum/servers_testnet.json
electrum_chi/electrum/simple_config.py
electrum_chi/electrum/storage.py
